helloapi/__init__.py
helloapi/__main__.py
helloapi/main.py
helloapi-0.1.0.dist-info/METADATA
helloapi-0.1.0.dist-info/WHEEL
helloapi-0.1.0.dist-info/entry_points.txt
helloapi-0.1.0.dist-info/RECORD
