Metadata-Version: 2.1
Name: helloapi
Version: 0.1.0
Summary: 
Author: Spenser Millburn
Author-email: spenser.millburn@alertinnovation.com
Requires-Python: >=3.8,<4.0
Classifier: Programming Language :: Python :: 3
Classifier: Programming Language :: Python :: 3.8
Classifier: Programming Language :: Python :: 3.9
Classifier: Programming Language :: Python :: 3.10
Classifier: Programming Language :: Python :: 3.11
Classifier: Programming Language :: Python :: 3.12
Requires-Dist: fastapi (>=0.111.0,<0.112.0)
Requires-Dist: uvicorn (>=0.30.1,<0.31.0)
